pytmtk/__init__.py
pytmtk/config.py
pytmtk/extract_data.py
pytmtk/runAll.py
pytmtk/sum_rouge_avg_result.py
pytmtk/__pycache__/__init__.cpython-36.pyc
pytmtk/__pycache__/config.cpython-36.pyc
pytmtk/__pycache__/runAll.cpython-36.pyc
pytmtk/kcllda/SmartStoplist.txt
pytmtk/kcllda/__init__.py
pytmtk/kcllda/llda.py
pytmtk/kcllda/llda_nltk.py
pytmtk/kcllda/rouge_score.py
pytmtk/kcllda/test.py
pytmtk/kcllda/__pycache__/llda.cpython-36.pyc
pytmtk/lda/__init__.py
pytmtk/lda/lda.py
pytmtk/lda/rouge_score.py
pytmtk/llda/__init__.py
pytmtk/llda/llda.py
pytmtk/llda/llda_nltk.py
pytmtk/llda/rouge_score.py
pytmtk/llda/__pycache__/llda.cpython-36.pyc
pytmtk/rake/SmartStoplist.txt
pytmtk/rake/__init__.py
pytmtk/rake/rake.py
pytmtk/rake/rouge_score.py
pytmtk/rake/__pycache__/rake.cpython-36.pyc
pytmtk/textrank/__init__.py
pytmtk/textrank/rouge_score.py
pytmtk/textrank/textrank_summa.py
pytmtk/tfidf/__init__.py
pytmtk/tfidf/rouge_score.py
pytmtk/tfidf/tfidf_main.py
pytmtk/tfidf/tfidf_main2.py
pytmtk/word_freq/__init__.py
pytmtk/word_freq/rouge_score.py
pytmtk/word_freq/word_freq.py
pytmtk-0.0.1.dist-info/LICENSE
pytmtk-0.0.1.dist-info/METADATA
pytmtk-0.0.1.dist-info/WHEEL
pytmtk-0.0.1.dist-info/top_level.txt
pytmtk-0.0.1.dist-info/RECORD
